{
  "hash": "814a6fb6",
  "configHash": "d8045afa",
  "lockfileHash": "150e6793",
  "browserHash": "2b671f51",
  "optimized": {
    "react": {
      "src": "../../node_modules/react/index.js",
      "file": "react.js",
      "fileHash": "76a5e18c",
      "needsInterop": true
    },
    "react-dom": {
      "src": "../../node_modules/react-dom/index.js",
      "file": "react-dom.js",
      "fileHash": "80b1293d",
      "needsInterop": true
    },
    "react-router-dom": {
      "src": "../../node_modules/react-router-dom/dist/index.js",
      "file": "react-router-dom.js",
      "fileHash": "87fe6de0",
      "needsInterop": false
    },
    "@supabase/supabase-js": {
      "src": "../../node_modules/@supabase/supabase-js/dist/module/index.js",
      "file": "@supabase_supabase-js.js",
      "fileHash": "4ade75c4",
      "needsInterop": false
    },
    "framer-motion": {
      "src": "../../node_modules/framer-motion/dist/es/index.mjs",
      "file": "framer-motion.js",
      "fileHash": "3fe217ed",
      "needsInterop": false
    },
    "@tanstack/react-query": {
      "src": "../../node_modules/@tanstack/react-query/build/modern/index.js",
      "file": "@tanstack_react-query.js",
      "fileHash": "4dcc7bb4",
      "needsInterop": false
    },
    "zustand": {
      "src": "../../node_modules/zustand/esm/index.mjs",
      "file": "zustand.js",
      "fileHash": "a43be0f1",
      "needsInterop": false
    },
    "zustand/middleware": {
      "src": "../../node_modules/zustand/esm/middleware.mjs",
      "file": "zustand_middleware.js",
      "fileHash": "a0c2ad5b",
      "needsInterop": false
    },
    "react/jsx-dev-runtime": {
      "src": "../../node_modules/react/jsx-dev-runtime.js",
      "file": "react_jsx-dev-runtime.js",
      "fileHash": "6cb46c7b",
      "needsInterop": true
    },
    "@hookform/resolvers/zod": {
      "src": "../../node_modules/@hookform/resolvers/zod/dist/zod.mjs",
      "file": "@hookform_resolvers_zod.js",
      "fileHash": "bd401b28",
      "needsInterop": false
    },
    "@radix-ui/react-accordion": {
      "src": "../../node_modules/@radix-ui/react-accordion/dist/index.mjs",
      "file": "@radix-ui_react-accordion.js",
      "fileHash": "2a8adb36",
      "needsInterop": false
    },
    "@radix-ui/react-alert-dialog": {
      "src": "../../node_modules/@radix-ui/react-alert-dialog/dist/index.mjs",
      "file": "@radix-ui_react-alert-dialog.js",
      "fileHash": "ac6b7862",
      "needsInterop": false
    },
    "@radix-ui/react-avatar": {
      "src": "../../node_modules/@radix-ui/react-avatar/dist/index.mjs",
      "file": "@radix-ui_react-avatar.js",
      "fileHash": "060908b9",
      "needsInterop": false
    },
    "@radix-ui/react-checkbox": {
      "src": "../../node_modules/@radix-ui/react-checkbox/dist/index.mjs",
      "file": "@radix-ui_react-checkbox.js",
      "fileHash": "481613da",
      "needsInterop": false
    },
    "@radix-ui/react-dialog": {
      "src": "../../node_modules/@radix-ui/react-dialog/dist/index.mjs",
      "file": "@radix-ui_react-dialog.js",
      "fileHash": "5fa98649",
      "needsInterop": false
    },
    "@radix-ui/react-dropdown-menu": {
      "src": "../../node_modules/@radix-ui/react-dropdown-menu/dist/index.mjs",
      "file": "@radix-ui_react-dropdown-menu.js",
      "fileHash": "c9f4c207",
      "needsInterop": false
    },
    "@radix-ui/react-icons": {
      "src": "../../node_modules/@radix-ui/react-icons/dist/react-icons.esm.js",
      "file": "@radix-ui_react-icons.js",
      "fileHash": "6206f5fb",
      "needsInterop": false
    },
    "@radix-ui/react-label": {
      "src": "../../node_modules/@radix-ui/react-label/dist/index.mjs",
      "file": "@radix-ui_react-label.js",
      "fileHash": "429a38bd",
      "needsInterop": false
    },
    "@radix-ui/react-popover": {
      "src": "../../node_modules/@radix-ui/react-popover/dist/index.mjs",
      "file": "@radix-ui_react-popover.js",
      "fileHash": "9a34c28b",
      "needsInterop": false
    },
    "@radix-ui/react-progress": {
      "src": "../../node_modules/@radix-ui/react-progress/dist/index.mjs",
      "file": "@radix-ui_react-progress.js",
      "fileHash": "727c29ac",
      "needsInterop": false
    },
    "@radix-ui/react-radio-group": {
      "src": "../../node_modules/@radix-ui/react-radio-group/dist/index.mjs",
      "file": "@radix-ui_react-radio-group.js",
      "fileHash": "6f03fe26",
      "needsInterop": false
    },
    "@radix-ui/react-scroll-area": {
      "src": "../../node_modules/@radix-ui/react-scroll-area/dist/index.mjs",
      "file": "@radix-ui_react-scroll-area.js",
      "fileHash": "4f0260a0",
      "needsInterop": false
    },
    "@radix-ui/react-select": {
      "src": "../../node_modules/@radix-ui/react-select/dist/index.mjs",
      "file": "@radix-ui_react-select.js",
      "fileHash": "c3bd15cc",
      "needsInterop": false
    },
    "@radix-ui/react-separator": {
      "src": "../../node_modules/@radix-ui/react-separator/dist/index.mjs",
      "file": "@radix-ui_react-separator.js",
      "fileHash": "a5031c47",
      "needsInterop": false
    },
    "@radix-ui/react-slot": {
      "src": "../../node_modules/@radix-ui/react-slot/dist/index.mjs",
      "file": "@radix-ui_react-slot.js",
      "fileHash": "fb1b2d22",
      "needsInterop": false
    },
    "@radix-ui/react-switch": {
      "src": "../../node_modules/@radix-ui/react-switch/dist/index.mjs",
      "file": "@radix-ui_react-switch.js",
      "fileHash": "56928baf",
      "needsInterop": false
    },
    "@radix-ui/react-tabs": {
      "src": "../../node_modules/@radix-ui/react-tabs/dist/index.mjs",
      "file": "@radix-ui_react-tabs.js",
      "fileHash": "68daae5e",
      "needsInterop": false
    },
    "@radix-ui/react-toast": {
      "src": "../../node_modules/@radix-ui/react-toast/dist/index.mjs",
      "file": "@radix-ui_react-toast.js",
      "fileHash": "b0525c88",
      "needsInterop": false
    },
    "@radix-ui/react-tooltip": {
      "src": "../../node_modules/@radix-ui/react-tooltip/dist/index.mjs",
      "file": "@radix-ui_react-tooltip.js",
      "fileHash": "ba73e1ed",
      "needsInterop": false
    },
    "@tanstack/react-table": {
      "src": "../../node_modules/@tanstack/react-table/build/lib/index.mjs",
      "file": "@tanstack_react-table.js",
      "fileHash": "3ffb212a",
      "needsInterop": false
    },
    "class-variance-authority": {
      "src": "../../node_modules/class-variance-authority/dist/index.mjs",
      "file": "class-variance-authority.js",
      "fileHash": "17d217ff",
      "needsInterop": false
    },
    "clsx": {
      "src": "../../node_modules/clsx/dist/clsx.mjs",
      "file": "clsx.js",
      "fileHash": "7cc57433",
      "needsInterop": false
    },
    "cmdk": {
      "src": "../../node_modules/cmdk/dist/index.mjs",
      "file": "cmdk.js",
      "fileHash": "de7d1254",
      "needsInterop": false
    },
    "date-fns": {
      "src": "../../node_modules/date-fns/index.mjs",
      "file": "date-fns.js",
      "fileHash": "35c39a77",
      "needsInterop": false
    },
    "date-fns/locale": {
      "src": "../../node_modules/date-fns/locale.mjs",
      "file": "date-fns_locale.js",
      "fileHash": "7eeb4d8b",
      "needsInterop": false
    },
    "exceljs": {
      "src": "../../node_modules/exceljs/dist/exceljs.min.js",
      "file": "exceljs.js",
      "fileHash": "06f51aa8",
      "needsInterop": true
    },
    "html2canvas": {
      "src": "../../node_modules/html2canvas/dist/html2canvas.esm.js",
      "file": "html2canvas.js",
      "fileHash": "f883119b",
      "needsInterop": false
    },
    "i18next": {
      "src": "../../node_modules/i18next/dist/esm/i18next.js",
      "file": "i18next.js",
      "fileHash": "694941ff",
      "needsInterop": false
    },
    "i18next-browser-languagedetector": {
      "src": "../../node_modules/i18next-browser-languagedetector/dist/esm/i18nextBrowserLanguageDetector.js",
      "file": "i18next-browser-languagedetector.js",
      "fileHash": "fa850beb",
      "needsInterop": false
    },
    "lucide-react": {
      "src": "../../node_modules/lucide-react/dist/esm/lucide-react.js",
      "file": "lucide-react.js",
      "fileHash": "89f3a1a3",
      "needsInterop": false
    },
    "react-countup": {
      "src": "../../node_modules/react-countup/build/index.js",
      "file": "react-countup.js",
      "fileHash": "a7b8aa32",
      "needsInterop": true
    },
    "react-day-picker": {
      "src": "../../node_modules/react-day-picker/dist/index.esm.js",
      "file": "react-day-picker.js",
      "fileHash": "ba676805",
      "needsInterop": false
    },
    "react-dom/client": {
      "src": "../../node_modules/react-dom/client.js",
      "file": "react-dom_client.js",
      "fileHash": "4b689e76",
      "needsInterop": true
    },
    "react-helmet-async": {
      "src": "../../node_modules/react-helmet-async/lib/index.esm.js",
      "file": "react-helmet-async.js",
      "fileHash": "3ecf50e4",
      "needsInterop": false
    },
    "react-hook-form": {
      "src": "../../node_modules/react-hook-form/dist/index.esm.mjs",
      "file": "react-hook-form.js",
      "fileHash": "d543d53b",
      "needsInterop": false
    },
    "react-i18next": {
      "src": "../../node_modules/react-i18next/dist/es/index.js",
      "file": "react-i18next.js",
      "fileHash": "b25b1f06",
      "needsInterop": false
    },
    "react-window": {
      "src": "../../node_modules/react-window/dist/index.esm.js",
      "file": "react-window.js",
      "fileHash": "615685f2",
      "needsInterop": false
    },
    "react-world-flags": {
      "src": "../../node_modules/react-world-flags/dist/react-world-flags.js",
      "file": "react-world-flags.js",
      "fileHash": "64329f16",
      "needsInterop": true
    },
    "react/jsx-runtime": {
      "src": "../../node_modules/react/jsx-runtime.js",
      "file": "react_jsx-runtime.js",
      "fileHash": "79b8f78f",
      "needsInterop": true
    },
    "tailwind-merge": {
      "src": "../../node_modules/tailwind-merge/dist/bundle-mjs.mjs",
      "file": "tailwind-merge.js",
      "fileHash": "9f8fcd58",
      "needsInterop": false
    },
    "zod": {
      "src": "../../node_modules/zod/lib/index.mjs",
      "file": "zod.js",
      "fileHash": "49015acd",
      "needsInterop": false
    },
    "zustand/middleware/immer": {
      "src": "../../node_modules/zustand/esm/middleware/immer.mjs",
      "file": "zustand_middleware_immer.js",
      "fileHash": "854cec2c",
      "needsInterop": false
    }
  },
  "chunks": {
    "browser-SMAFJRWN": {
      "file": "browser-SMAFJRWN.js"
    },
    "browser-FKWMLYPV": {
      "file": "browser-FKWMLYPV.js"
    },
    "chunk-GA6IJS2I": {
      "file": "chunk-GA6IJS2I.js"
    },
    "chunk-AREIMVPS": {
      "file": "chunk-AREIMVPS.js"
    },
    "chunk-HQ6ZTAWL": {
      "file": "chunk-HQ6ZTAWL.js"
    },
    "chunk-IWI4RDZI": {
      "file": "chunk-IWI4RDZI.js"
    },
    "chunk-EA3IJGTN": {
      "file": "chunk-EA3IJGTN.js"
    },
    "chunk-TCQMTAGU": {
      "file": "chunk-TCQMTAGU.js"
    },
    "chunk-GVBFZSPE": {
      "file": "chunk-GVBFZSPE.js"
    },
    "chunk-EOBE3EPS": {
      "file": "chunk-EOBE3EPS.js"
    },
    "chunk-EI7GKQK4": {
      "file": "chunk-EI7GKQK4.js"
    },
    "chunk-IZSHHM6I": {
      "file": "chunk-IZSHHM6I.js"
    },
    "chunk-USILINJZ": {
      "file": "chunk-USILINJZ.js"
    },
    "chunk-RXAZMTH6": {
      "file": "chunk-RXAZMTH6.js"
    },
    "chunk-NBJXNFOV": {
      "file": "chunk-NBJXNFOV.js"
    },
    "chunk-VPWNYQQC": {
      "file": "chunk-VPWNYQQC.js"
    },
    "chunk-EHWKTTJO": {
      "file": "chunk-EHWKTTJO.js"
    },
    "chunk-FNFGFQ3F": {
      "file": "chunk-FNFGFQ3F.js"
    },
    "chunk-PPCZUJRX": {
      "file": "chunk-PPCZUJRX.js"
    },
    "chunk-STIMPWYK": {
      "file": "chunk-STIMPWYK.js"
    },
    "chunk-XOVHPL4B": {
      "file": "chunk-XOVHPL4B.js"
    },
    "chunk-SWXTNEUO": {
      "file": "chunk-SWXTNEUO.js"
    },
    "chunk-B3IKTMMM": {
      "file": "chunk-B3IKTMMM.js"
    },
    "chunk-WR4VNMO6": {
      "file": "chunk-WR4VNMO6.js"
    },
    "chunk-FN2YEC6U": {
      "file": "chunk-FN2YEC6U.js"
    },
    "chunk-XBZMPOVV": {
      "file": "chunk-XBZMPOVV.js"
    },
    "chunk-M3F4TZDX": {
      "file": "chunk-M3F4TZDX.js"
    },
    "chunk-3I6JAFN6": {
      "file": "chunk-3I6JAFN6.js"
    },
    "chunk-PLQOC46F": {
      "file": "chunk-PLQOC46F.js"
    },
    "chunk-NZAIND7N": {
      "file": "chunk-NZAIND7N.js"
    },
    "chunk-UVNPGZG7": {
      "file": "chunk-UVNPGZG7.js"
    },
    "chunk-OL46QLBJ": {
      "file": "chunk-OL46QLBJ.js"
    }
  }
}